tabtest/__init__.py
tabtest/models/__init__.py
tabtest/models/calculated_fields.py
tabtest/models/dashboard.py
tabtest/models/datasource.py
tabtest/models/filters.py
tabtest/models/formatting.py
tabtest/models/parameters.py
tabtest/models/sets.py
tabtest/models/workbook.py
tabtest/models/worksheet.py
tabtest/parser/__init__.py
tabtest/parser/dashboard_parser.py
tabtest/parser/datasource_parser.py
tabtest/parser/reference_resolver.py
tabtest/parser/workbook_parser.py
tabtest/parser/worksheet_parser.py
tabtest/parser/xml_loader.py
tabtest/suite/__init__.py
tabtest/suite/fixtures.py
tabtest/suite/helpers.py
tabtest-0.1.0.dist-info/licenses/LICENCE.txt
tabtest-0.1.0.dist-info/METADATA
tabtest-0.1.0.dist-info/WHEEL
tabtest-0.1.0.dist-info/top_level.txt
tabtest-0.1.0.dist-info/RECORD
