Metadata-Version: 2.4
Name: tabtest
Version: 0.1.0
Summary: Tableau の .twb .twbx ファイルを解析・テストするツール
Author-email: Kamegrueon <niwaniwaniwaniwatori.gairuze@gmail.com>
License: MIT
Project-URL: Documentation, https://github.com/Kamegrueon/tabtest#readme
Project-URL: Homepage, https://github.com/Kamegrueon/tabtest
Project-URL: Issues, https://github.com/Kamegrueon/tabtest/issues
Project-URL: Repository, https://github.com/Kamegrueon/tabtest
Keywords: tableau,twb,twbx,parser,testing
Classifier: Development Status :: 3 - Alpha
Classifier: Intended Audience :: Developers
Classifier: License :: OSI Approved :: MIT License
Classifier: Programming Language :: Python :: 3
Classifier: Programming Language :: Python :: 3.12
Classifier: Topic :: Software Development :: Testing
Classifier: Topic :: Text Processing :: Markup :: XML
Requires-Python: >=3.12
License-File: LICENCE.txt
Requires-Dist: lxml>=5.4.0
Requires-Dist: pydantic>=2.11.7
Requires-Dist: pytest>=8.4.1
Dynamic: license-file
